msteams/__init__.py
msteams-0.1.0.dist-info/LICENSE
msteams-0.1.0.dist-info/METADATA
msteams-0.1.0.dist-info/WHEEL
msteams-0.1.0.dist-info/top_level.txt
msteams-0.1.0.dist-info/RECORD
