Metadata-Version: 2.1
Name: msteams
Version: 0.1.0
Summary: A builder/formatter for MS Teams cards
Home-page: https://github.com/johanjeppsson/msteams
Author: Johan Jeppsson
Author-email: johjep@gmail.com
License: UNKNOWN
Platform: UNKNOWN
Classifier: Programming Language :: Python :: 3
Classifier: License :: OSI Approved :: MIT License
Classifier: Operating System :: OS Independent
Requires-Python: >=2.7
